Metadata-Version: 2.1
Name: textconfig
Version: 0.1
Summary: Simple text configuration file reading/writing
Home-page: https://github.com/gapan/textconfig
Author: George Vlahavas
Author-email: vlahavas@gmail.com
License: GPLv3
Platform: Platform Independent
Classifier: Development Status :: 5 - Production/Stable
Classifier: Intended Audience :: Developers
Classifier: License :: OSI Approved :: GNU General Public License v3 (GPLv3)
Classifier: Operating System :: OS Independent
Classifier: Programming Language :: Python :: 2.7
Classifier: Programming Language :: Python :: 3
Classifier: Topic :: Software Development :: Libraries
